adafruit_circuitpython_gizmo-1.3.25.dist-info/licenses/LICENSE
adafruit_gizmo/__init__.py
adafruit_gizmo/eink_gizmo.py
adafruit_gizmo/tft_gizmo.py
adafruit_circuitpython_gizmo-1.3.25.dist-info/METADATA
adafruit_circuitpython_gizmo-1.3.25.dist-info/WHEEL
adafruit_circuitpython_gizmo-1.3.25.dist-info/top_level.txt
adafruit_circuitpython_gizmo-1.3.25.dist-info/RECORD
