Metadata-Version: 2.4
Name: adafruit-circuitpython-gizmo
Version: 1.3.25
Summary: CircuitPython classes for Adafruit Gizmos
Author-email: Adafruit Industries <circuitpython@adafruit.com>
License: MIT
Project-URL: Homepage, https://github.com/adafruit/Adafruit_CircuitPython_Gizmo
Keywords: adafruit,blinka,circuitpython,micropython,gizmo,circuit,playground
Classifier: Intended Audience :: Developers
Classifier: Topic :: Software Development :: Libraries
Classifier: Topic :: Software Development :: Embedded Systems
Classifier: Topic :: System :: Hardware
Classifier: License :: OSI Approved :: MIT License
Classifier: Programming Language :: Python :: 3
License-File: LICENSE
Requires-Dist: Adafruit-Blinka
Requires-Dist: adafruit-circuitpython-busdevice
Requires-Dist: adafruit-circuitpython-st7789
Requires-Dist: adafruit-circuitpython-il0373
Requires-Dist: adafruit-circuitpython-ssd1681
Provides-Extra: optional
Dynamic: license-file
